{"name":"Chef SolrCloud","tagline":"Chef cookbook to Manage Apache SolrCloud","body":"solrcloud Cookbook\r\n==================\r\n\r\nThis is a [Chef] cookbook for [Apache Solr].\r\n\r\nIt was primarily developed for Testing SolrCloud against Solr Master/Slave setup and its features.\r\n\r\nCurrently it supports only in built Jetty based SolrCloud deployment, more\r\nfeatures and attributes will be added over time, **feel free to contribute**\r\nwhat you find missing!\r\n\r\nSolrCloud is the default deployment and Solr Master/Slave setup is not supported\r\nby this cookbook.\r\n\r\n\r\n## Repository\r\n\r\nhttps://github.com/vkhatri/chef-solrcloud\r\n\r\n\r\n## Supported Apache Solr Version\r\n\r\nThis cookbook was tested for Apache Solr 4.9.0. Minimal setup was tested for v4.10.x.\r\n\r\n\r\n## Supported Apache Solr Runtime\r\n\r\nCurrently this cookbook supports only Apache Solr in built [Jetty] based deployment.\r\n\r\n\r\n## Supported Apache Solr Package Deployment\r\n\r\nCurrently this cookbook only supports Apache Solr Tarball based deployment.\r\n\r\n\r\n## Supported Apache Solr Cluster Deployment\r\n\r\nCurrently this cookbook only support SolrCloud Cluster deployment. It does not\r\nsupport Apache Solr Master/Slave Cluster deployment.\r\n\r\n\r\n## Supported JDK Versions\r\n\r\nCheck [Apache Solr] Documentation for JDK Version requirement for current Solr version, Oracle JDK 7 is recommended.\r\n\r\n\r\n## Recipes\r\n\r\n- `solrcloud::tarball`     \t- install solr package, directories and service\r\n\r\n- `solrcloud::config`  \t\t- manages solr base configuration files\r\n\r\n- `solrcloud::jetty`   \t\t- manages jetty base configuration files and directories\r\n\r\n- `solrcloud::zkcli`\t\t- setup zookeeper package for zookeeper client binary (zkCli.sh)\r\n\r\n\t\tzkcli recipe does not manage zookeeper server and its only purpose\r\n\t\tis to have zookeeper client on all solr nodes\r\n\r\n- `solrcloud::user`\t\t\t- create solr service user\r\n\r\n\t\tsolr user is better to be managed by a User management cookbook\r\n\t\tinstead of solrcloud for Production environment.\r\n\r\n- `solrcloud::zkconfigsets`\t- create/delete solrcloud configSet in zookeeper via LWRP\r\n\r\n- `solrcloud::collections` \t- create/delete solrcloud collection on solrcloud node via LWRP\r\n\r\n\r\n> `solrcloud::tarball` is the main recipe which includes all other recipe. For `run_list` use `solrcloud::tarball`.\r\n\r\n\r\n## SolrCloud configSet (Zookeeper Configs) LWRP\r\n\r\n\r\n**LWRP - solrcloud_zkconfigset**\r\n\r\nSolrCloud Zookeeper configSet is managed via LWRP - `solrcloud_zkconfigset`.\r\n\r\nSolrCloud Zookeeper configSets management is enabled by default for all nodes.\r\nIt means all nodes will get the configSets and will try to manage it against\r\none of the configured zookeeper server via attribute `node[:solrcloud][:solr_config][:solrcloud][:zk_host]`.\r\n\r\n    All the nodes communicate to a zookeeper cluster, hence attribute\r\n    `node[:solrcloud][:manage_zkconfigsets]` & `node[:solrcloud][:manage_zkconfigsets_source]`\r\n    does not require to be enabled on all the nodes.\r\n\r\nCheck `Cookbook Advanced Attributes` section for attribute details.\r\n\r\n\r\n**zookeeper configSet config changes**\r\n\r\nLWRP handles config changes by itself. When any change is made to configSet content, configSet will re-upload configSet to zookeeper.\r\n\r\n\r\n**LWRP example**\r\n\r\n*Create a configSet using LWRP:*\r\n\r\n    solrcloud_zkconfigset configset_name\r\n      option option_name\r\n    end\r\n\r\n\r\n*Always re create/upload configSet even exists or no update to config files:*\r\n\r\n    solrcloud_zkconfigset configset_name\r\n      force_upload true\r\n      option option_name\r\n    end\r\n\r\nOR\r\n\r\nSet attribute `node[:solrcloud][:force_zkconfigsets_upload]` to true, which affects all the configSets as\r\nresource attribute :force_upload defualt value is set to `node[:solrcloud][:force_zkconfigsets_upload]`.\r\n\r\n\r\n*Delete a configSet using LWRP:*\r\n\r\n    solrcloud_zkconfigset configset_name do\r\n      action :delete\r\n    end\r\n\r\n\r\n*configSet via node attribute:*\r\n\r\n    \"default_attributes\": {\r\n      \"solrcloud\": {\r\n        \"zkconfigsets\": {\r\n          \"abc\": {\r\n            \"action\": \"delete\"\r\n          },\r\n          \"xyz\": {\r\n\t        \"option name\": \"option value\"\r\n          }\r\n        }\r\n      }\r\n    }\r\n\r\n> configSets can either be configured in recipe using LWRP or using node attribute `node[:solrcloud][:zkconfigsets]`.\r\n\r\n> configSets defined using attribute `node[:solrcloud][:zkconfigsets]` does not require LWRP.\r\n\r\n\r\n**LWRP Options**\r\n\r\nSolrCloud Zookeeper cmd Reference: https://cwiki.apache.org/confluence/display/solr/Command+Line+Utilities\r\n\r\nParameters:\r\n\r\n- *configset_name (required)*\t\t\t- solrcloud zookeeper configSet name\r\n- *action (optional)*\t\t\t\t\t- default :create\r\n- *user (optional)*\t\t\t\t\t\t- configSet directory user permission, default value `node[:solrcloud][:user]`\r\n- *group (optional)*\t\t\t\t\t- configSet directory group permission, default value `node[:solrcloud][:group]`\r\n- *solr_zkcli (optional)*\t\t\t\t- solr in built zkcli.sh for configSet upconfig, default value `node[:solrcloud][:zookeeper][:solr_zkcli]`\r\n- *zkcli (optional)*\t\t\t\t\t- zookeeper client zkCli.sh, default value `node[:solrcloud][:zookeeper][:zkcli]`\r\n- *zkhost (optional)*\t\t\t\t\t- zookeeper server, default value `node[:solrcloud][:solr_config][:solrcloud][:zk_host].first`\r\n- *zkconfigsets_home (optional)*\t\t- configSet directory to sore on solrcloud node, default value `node[:solrcloud][:zkconfigsets_home]`\r\n- *zkconfigsets_cookbook (optional)*\t- configSet cookbook name, default value `node[:solrcloud][:zkconfigsets_cookbook]`\r\n- *manage_zkconfigsets (optional)* - manage configSet, default value `node[:solrcloud][:manage_zkconfigsets]`\r\n- *force_upload (optional)* - if set always upload configSet to zookeeper, default value `node[:solrcloud][:force_zkconfigsets_upload]`\r\n\r\n**LWRP configSet source cookbook/location management**\r\n\r\nAll configSet content must be stored under `node[:solrcloud][:zkconfigsets_cookbook]`/files/default/config set name/conf/` if\r\nnot managed separately.\r\n\r\nconfigSets source cookbook is default set to `solrcloud` and can be changed via attribute `node[:solrcloud][:zkconfigsets_cookbook]`.\r\n\r\nIf configSets are managed outside of the cookbook, configSet will only get uploaded in case it is missing in the zookeeper.\r\nAny update to separately managed configSets are not propogated to zookeeper by default. However, one can use attribute\r\n`node[:solrcloud][:force_zkconfigsets_upload]` to always upload the configSet regardless of the state.\r\n\r\n> Setting attribute node[:solrcloud][:force_zkconfigsets_upload] or resource attribute :force_upload would always trigger configSet upload to zookeeper. It is better not to enable rsource attribute :force_upload, but instead better to use attribute node[:solrcloud][:force_zkconfigsets_upload] on limited set of nodes.\r\n\r\n> This may vary environment to environment.\r\n\r\n\r\n## SolrCloud Collection LWRP\r\n\r\n**LWRP - solrcloud_collection**\r\n\r\nSolrCloud collection is managed via LWRP - `solrcloud_collection`.\r\n\r\n> Create/Delete Collection API does not require to run on all solrcloud cluster nodes, hence attribute\r\n\r\n> `node[:solrcloud][:manage_collections]` does not require to be enabled on all the nodes.\r\n\r\nCheck `Cookbook Advanced Attributes` section for attribute details.\r\n\r\n\r\n**collection Update/Change**\r\n\r\ncollection LWRP only perform collection action=CREATE|DELETE and does not manage any UPDATE/change in the collection.\r\n\r\nTo make a change to a collection, first make the change in the LWRP or node attribute `node[:solrcloud][:collections][:collection_nam][:attribute_name]`\r\nfor respective attribute.\r\n\r\nOnce changes are made in Chef cookbook, perform collection UPDATE or respective action call to one of the solrcloud node.\r\n\r\nUPDATE call could be tricky and is not managed by Chef to avoid any unexpected behavior.\r\n\r\nRe-issuing same command could hinder solrcloud cluster setup and must be re-issued carefully.\r\n\r\n\r\n**LWRP example**\r\n\r\n*Create a collection using LWRP:*\r\n\r\n    solrcloud_collection collection_name\r\n      option option_name\r\n    end\r\n\r\n\r\n*Delete a collection using LWRP:*\r\n\r\n    solrcloud_collection collection_name do\r\n      action :delete\r\n    end\r\n\r\n\r\n*collection via node attribute:*\r\n\r\n    \"default_attributes\": {\r\n      \"solrcloud\": {\r\n        \"collections\": {\r\n          \"abc\": {\r\n            \"action\": \"delete\"\r\n          },\r\n          \"xyz\": {\r\n            \"num_shards\": \"1\",\r\n            \"name\": \"xyz\",\r\n            \"replication_factor\": \"1\",\r\n            \"collection_config_name\": \"xyz\",\r\n            \"option name\": \"value\"\r\n          }\r\n\t    }\r\n      }\r\n    }\r\n\r\n\r\n> collections can either be configured in recipe using LWRP or using node attribute `node[:solrcloud][:collections]`.\r\n\r\n> collections defined using attribute `node[:solrcloud][:collections]` does not require LWRP.\r\n\r\n\r\n**LWRP Options**\r\n\r\nCollection API Reference: https://cwiki.apache.org/confluence/display/solr/Collections+API\r\n\r\n\r\nParameters:\r\n\r\n- *collection_config_name* (required)\t\t\t- solrcloud zookeeper configSet name\r\n- *action* (optional)\t\t\t\t\t\t\t- default :create\r\n- *num_shards* (optional)\t\t\t\t\t\t- collection API parameter numShards, default value 1\r\n- *shards* (optional)\t\t\t\t\t\t\t- collection API parameter shards, default value nil\r\n- *router_field* (optional)\t\t\t\t\t\t- collection API parameter router.field, default value nil\r\n- *async* (optional)\t\t\t\t\t\t\t- collection API parameter async, default value nil\r\n- *router_name* (optional)\t\t\t\t\t\t- collection API parameter router.name, default value nil\r\n- *router_field* (optional)\t\t\t\t\t\t- collection API parameter router.field, default value nil\r\n- *host* (optional)\t\t\t\t\t\t\t\t- collection API host, solrcloud node (self), default value `node[:ipaddress]`\r\n- *use_ssl* (optional)\t\t\t\t\t\t- collection API, use https, default value false\r\n- *port* (optional)\t\t\t\t\t\t\t\t- collection API host port, solrcloud port, default value `node[:solrcloud][:port]`\r\n- *ssl_port_* (optional)\t\t\t\t\t\t- collection API host ssl port, default value `node[:solrcloud][:ssl_port]`\r\n- *create_node_set* (optional)\t\t\t\t\t- collection API parameter createNodeSet, default value nil\r\n- *replication_factor* (optional)\t\t\t\t- collection API parameter replicationFactor, default value 1\r\n- *max_shards_per_node* (optional)\t\t\t\t- collection API parameter maxShardsPerNode, default value nil\r\n- *auto_add_replicas* (optional)\t\t\t\t- collection API parameter autoAddReplicas, default value false\r\n\r\n\r\n## Cookbook Advanced Attributes\r\n\r\n * `default[:solrcloud][:manage_zkconfigsets]` (default: `true`): manages solrcloud configSets in zookeeper\r\n\r\n    This attribute should be enabled for limited nodes in solrcloud cluster if possible.\r\n\r\n * `default[:solrcloud][:manage_zkconfigsets_source]` (default: `true`): manages solrcloud collections configSets source content directory\r\n\r\n    This attribute should be enabled for limited nodes in solrcloud cluster if possible.\r\n\r\n * `default[:solrcloud][:notify_zkconfigsets_upload]` (default: `true`): notify/triggers configSet upload to zookeeper upon create/update\r\n\r\n    This attribute should be enabled for limited nodes in solrcloud cluster if possible.\r\n\r\n * `default[:solrcloud][:manage_collections]` (default: `true`): if set true, manages solrcloud cluster collections\r\n\r\n    This attribute should be enabled for limited nodes in solrcloud cluster if possible.\r\n\r\n * `default[:solrcloud][:notify_restart]` (default: `false`): notify solr service on a solrcloud resource change like config file/template etc.\r\n\r\n * `default[:solrcloud][:zk_run]` (default: `false`): if true solr will start up with embedded zookeeper\r\n\r\n    Note: Setting option `node[:solrcloud][:zk_run]` will remove solrcloud config zk_host from solr.xml, mainly meant for testing purpose\r\n\r\n * `default[:solrcloud][:enable_jmx]` (default: `true`): enable jmx\r\n\r\n * `default[:solrcloud][:port]` (default: `8983`): solr service port, must be (>1024 for non root user)\r\n\r\n * `default[:solrcloud][:ssl_port]` (default: `8984`): solr ssl service port (>1024 for non root user)\r\n\r\n * `default[:solrcloud][:enable_ssl]` (default: `true`): enable solr ssl connector\r\n\r\n * `default[:solrcloud][:enable_request_log]` (default: `true`): enable request log\r\n\r\n * `default[:solrcloud][:solr_config][:solrcloud][:zk_host]` (default: `[]`): zookeeper servers, e.g. `[\"server:port\", \"server:port\"]`\r\n\r\n    With attribute `default[:solrcloud][:zk_run]`, this attribute will get local zookeeper server.\r\n\r\n * `default[:solrcloud][:java_options]` (default: `[]`): java options\r\n\r\n * `default[:solrcloud][:auto_java_memory]` (default: `true`): enable auto java memory allocation, sets java attribute `-Xmx` for `node[:solrcloud][:java_options]`\r\n\r\n\t\tThis option calculates maximum allowed memory (multiple of 1024) for java\r\n\t\tprocess with minimum system memory reservation defined by attribute\r\n\t\t`node[:solrcloud][:auto_system_memory]`\r\n\r\n * `default[:solrcloud][:auto_system_memory]` (default: `768`): memory to preserve for OS, required when attribute `default[:solrcloud][:auto_java_memory]` is set\r\n\r\n * `default[:solrcloud][:install_java]` (default: `true`): setup java, disable to manage java outside of this cookbook\r\n\r\n * `default[:solrcloud][:force_zkconfigsets_upload]` (default: `false`): if set, zkconfigset lwrp will always execute configSet upload\r\n    to zookeeper even configSet exists or there is no update. This option is useful when configSet source directory is managed\r\n    separately.\r\n\r\n    This attribute should be enabled for limited nodes in solrcloud cluster if possible.\r\n\r\n## Cookbook Core Attributes\r\n\r\n * `default[:solrcloud][:user]` (default: `solr`): solr service user\r\n * `default[:solrcloud][:group]` (default: `solr`): solr service group\r\n * `default[:solrcloud][:user_home]` (default: `nil`): solr service user home\r\n\r\n * `default[:solrcloud][:setup_user]` (default: `true`): manage solr user for solr service using `solrcloud::user` cookbook\r\n\r\n * `default[:solrcloud][:version]` (default: `4.9.0`): solr package version\r\n\r\n * `default[:solrcloud][:zk_run_data_dir]` (default: `node[:solrcloud][:install_dir]/zookeeperdata`): embedded zookeeper data directory\r\n * `default[:solrcloud][:zk_run_port]` (default: `2181`): embedded zookeeper port\r\n\r\n * `default[:solrcloud][:install_dir]` (default: `/usr/local/solr`): jetty home directory - jetty.home\r\n * `default[:solrcloud][:data_dir]` (default: `/opt/solr`): solr collection data directory - solr.data.dir\r\n\r\n    solrconfig.xml for each configSet needs to set dataDir for this location usage, like:\r\n    <dataDir>${solr.data.dir:}/collection name</dataDir>\r\n\r\n * `default[:solrcloud][:solr_home]` (default: `node[:solrcloud][:install_dir]/solr`): solr home\r\n * `default[:solrcloud][:cores_home]` (default: `node[:solrcloud][:solr_home]/cores`): solr collection/core home\r\n * `default[:solrcloud][:shared_lib]` (default: `node[:solrcloud][:install_dir]`/lib): solr default lib directory\r\n * `default[:solrcloud][:config_sets]` (default: `node[:solrcloud][:solr_home]/configsets`): solr cores configSets directory\r\n\r\n * `default[:solrcloud][:service_name]` (default: `solr`): solr service name\r\n * `default[:solrcloud][:service_start_wait]` (default: `15`): solr server after start up wait time\r\n * `default[:solrcloud][:dir_mode]` (default: `0755`): solr resource default directory\r\n\r\n * `default[:solrcloud][:pid_dir]` (default: `/var/run/solr`): solr pid directory\r\n * `default[:solrcloud][:log_dir]` (default: `/var/log/solr`): solr log directory\r\n\r\n * `default[:solrcloud][:template_cookbook]` (default: `solrcloud`): solr template resources cookbook\r\n * `default[:solrcloud][:zkconfigsets_cookbook]` (default: `solrcloud`): zookeeper configSet cookbook\r\n * `default[:solrcloud][:zkconfigsets_home]` (default: `node[:solrcloud][:install_dir]/zkconfigs`): configs location for zookeeper configSet upconfig\r\n\r\n * `default[:solrcloud][:zookeeper][:version]` (default: `3.4.6`): zookeeper package setup for zkCli.sh\r\n\r\n\r\n## Cookbook Ulimit Attributes\r\n\r\n * `default[:solrcloud][:limits][:memlock]` (default: `unlimited`): solr service user memory limit\r\n * `default[:solrcloud][:limits][:nofile]` (default: `48000`): solr service user file limit\r\n * `default[:solrcloud][:limits][:nproc]` (default: `unlimited`): solr service user process limit\r\n\r\n\r\n## Cookbook log4j.properties Config Attributes\r\n\r\n * `default[:solrcloud][:log4j][:level]` (default: `10MB`):  solr log threshold\r\n * `default[:solrcloud][:log4j][:console]` (default: `false`): enable/disable CONSOLE log\r\n * `default[:solrcloud][:log4j][:max_file_size]` (default: `10MB`):  maximum log file size\r\n * `default[:solrcloud][:log4j][:max_backup_index]` (default: `10`): log files retention\r\n * `default[:solrcloud][:log4j][:conversion_pattern]` (default: `'%d{ISO8601} [%t] %-5p %c{3} %x - %m%n'`): log conversion pattern\r\n\r\n## Cookbook Request Log Config Attributes\r\n\r\n * `default[:solrcloud][:request_log][:retain_days]` (default: `10`): request log files retention\r\n * `default[:solrcloud][:request_log][:log_cookies]` (default: `false`):  enable log cookies\r\n * `default[:solrcloud][:request_log][:time_zone]` (default: `UTC`): request log time zone\r\n\r\n## Cookbook Jetty Core Server Attributes\r\n\r\n * `default[:solrcloud][:jetty_config][:server][:min_threads]` (default: `10`): minimum jetty threads\r\n * `default[:solrcloud][:jetty_config][:server][:max_threads]` (default: `10000`): maximum jetty threads\r\n * `default[:solrcloud][:jetty_config][:server][:detailed_dump]` (default: `false`): enable jetty detailed dump\r\n\r\n## Cookbook Jetty Default Connector Attributes (org.eclipse.jetty.server.bio.SocketConnector)\r\n\r\n * `default[:solrcloud][:jetty_config][:connector][:stats_on]` (default: `true`): enable statistics\r\n * `default[:solrcloud][:jetty_config][:connector][:max_idle_time]` (default: `50000`): max idle time for connector (http)\r\n * `default[:solrcloud][:jetty_config][:connector][:low_resource_max_idle_time]` (default: `1500`):\r\n\r\n## Cookbook Jetty SSL Connector Attributes\r\n\r\n * `default[:solrcloud][:jetty_config][:ssl_connector][:need_client_auth]` (default: `false`): enable client ssl authentication, this feature is not tested yet\r\n * `default[:solrcloud][:jetty_config][:ssl_connector][:max_idle_time]` (default: `30000`): jetty ssl maximum idle time\r\n\r\n\r\n## Cookbook Jetty SSL Key Store Attributes\r\n\r\n * `default[:solrcloud][:key_store][:manage]` (default: `true`): generate key store for node key store attribute (enabled for testing purpose)\r\n * `default[:solrcloud][:key_store][:key_store_file]` (default: `solr.keystore`): key store file name, file location - node.solrcloud.install_dir/resources/etc/\r\n * `default[:solrcloud][:key_store][:key_store_password]` (default: ``): key store password\r\n * `default[:solrcloud][:key_store][:cookbook]` (default: `solrcloud`): jetty ssl key store source cookbook, required is cookbook filekey store file management is disabled. Typical for Production environment.\r\n * `default[:solrcloud][:key_store][:key_algo]` (default: `RSA`): key store Algorithm\r\n * `default[:solrcloud][:key_store][:cn]` (default: `localhost`): key store CN\r\n * `default[:solrcloud][:key_store][:ou]` (default: `ApacheSolrCloudTest`): key store OU\r\n * `default[:solrcloud][:key_store][:o]` (default: `lucene.apache.org`): key store O\r\n * `default[:solrcloud][:key_store][:c]` (default: `US`): key store C\r\n * `default[:solrcloud][:key_store][:ext]` (default: `san=ip:127.0.0.1`): key store ext params\r\n * `default[:solrcloud][:key_store][:validity]` (default: `999999`): key store validity\r\n\r\n## Cookbook Jetty JMX Attributes\r\n\r\n * `default[:solrcloud][:jmx][:port]` (default: `1099`): jmx port\r\n * <del>`default[:solrcloud][:jmx][:ssl]` (default: `false`): this feature is not available yet and disabled</del>\r\n * <del>`default[:solrcloud][:jmx][:authenticate]` (default: `false`): enable jmx authentication and authorization, this feature is not tested yet</del>\r\n * `default[:solrcloud][:jmx][:users]` (default: `users - solrmonitor solrconfig`): jmx defaults users and roles, this feature is not tested yet\r\n\r\n## Cookbook Jetty Context Attributes\r\n * `default[:solrcloud][:jetty_config][:context][:path]` (default: `/solr`): solr default context path\r\n * `default[:solrcloud][:jetty_config][:context][:temp_directory]` (default: `/solr-webapp`): solr webapp directory\r\n * `default[:solrcloud][:jetty_config][:context][:war]` (default: `/webapps/solr.war`): jetty webapp solr war file location\r\n\r\n## Cookbook solr.xml Config Attributes\r\n\r\nsolr.xml Reference: https://cwiki.apache.org/confluence/display/solr/Format+of+solr.xml\r\n\r\n * `default[:solrcloud][:solr_config][:admin_handler]` (default: `org.apache.solr.handler.admin.CoreAdminHandler`): solr.xml solr param adminHandler\r\n * `default[:solrcloud][:solr_config][:admin_path]` (default: `/solr/admin`): solr.xml param adminPath\r\n * `default[:solrcloud][:solr_config][:core_load_threads]` (default: `3`): solr.xml solr param coreLoadThreads\r\n * `default[:solrcloud][:solr_config][:core_root_directory]` (default: `node[:solrcloud][:cores_home]`): solr.xml solr param coreRootDirectory\r\n * `default[:solrcloud][:solr_config][:shared_lib]` (default: `node[:solrcloud][:shared_lib]`): solr.xml solr param sharedLib\r\n * `default[:solrcloud][:solr_config][:management_path]` (default: `nil`): solr.xml solr param managementPath\r\n * `default[:solrcloud][:solr_config][:share_schema]` (default: `false`): solr.xml solr param shareSchema\r\n * `default[:solrcloud][:solr_config][:transient_cache_size]` (default: `1000000`): solr.xml solr param transientCacheSize\r\n * `default[:solrcloud][:solr_config][:solrcloud][:host_context]` (default: `solr`): solr.xml param solrcloud hostContext\r\n * `default[:solrcloud][:solr_config][:solrcloud][:distrib_update_conn_timeout]` (default: `1000000`): solr.xml param solrcloud distribUpdateConnTimeout\r\n * `default[:solrcloud][:solr_config][:solrcloud][:distrib_update_so_timeout]` (default: `1000000`): solr.xml param solrcloud distribUpdateSoTimeout\r\n * `default[:solrcloud][:solr_config][:solrcloud][:leader_vote_wait]` (default: `1000000`): solr.xml param solrcloud leaderVoteWait\r\n * `default[:solrcloud][:solr_config][:solrcloud][:zk_client_timeout]` (default: `15000`): solr.xml param solrcloud zkClientTimeout\r\n * `default[:solrcloud][:solr_config][:solrcloud][:zk_host]` (default: `[]`): zookeeper servers, e.g. `[\"server:port\", \"server:port\"]`\r\n * `default[:solrcloud][:solr_config][:solrcloud][:generic_core_node_names]` (default: `true`): solr.xml param solrcloud genericCoreNodeNames\r\n * `default[:solrcloud][:solr_config][:shard_handler_factory][:socket_timeout]` (default: `0`): solr.xml param shardHandlerFactory socketTimeout\r\n * `default[:solrcloud][:solr_config][:shard_handler_factory][:conn_timeout]` (default: `0`): solr.xml param shardHandlerFactory connTimeout\r\n * </del>`default[:solrcloud][:solr_config][:logging][:enabled]` (default: `false`): solr.xml param logging enabled, not required</del>\r\n * </del>`default[:solrcloud][:solr_config][:logging][:logging_class]` (default: `nil`): solr.xml param logging class, not required </del>\r\n * </del>`default[:solrcloud][:solr_config][:logging][:watcher][:logging_size]` (default: `1000`): solr.xml param logging size, not required</del>\r\n * </del>`default[:solrcloud][:solr_config][:logging][:watcher][:threshold]` (default: `INFO`): solr.xml param logging threshold, no required</del>\r\n\r\n\r\n## Cookbook SolrCloud on HDFS Config Attributes\r\n\r\n * `default[:solrcloud][:hdfs][:enable]` (default: `false`): to run solrcloud on hdfs, set it to `true`\r\n * `default[:solrcloud][:hdfs][:directory_factory]` (default: `HdfsDirectoryFactory`):\r\n * `default[:solrcloud][:hdfs][:lock_type]` (default: `hdfs`):\r\n * `default[:solrcloud][:hdfs][:hdfs_home]` (default: `nil`): syntax: 'hdfs://host:port/path'\r\n\r\n> Note: SolrCloud on HDFS Deployment using this cookbook is not yet tested, check online [solr on hdfs] for more info\r\n\r\n\r\n## Cookbook Dependencies\r\n\r\n* `ulimit` cookbook\r\n* `java` cookbook\r\n\r\n\r\n## SolrCloud Deployment Requirement\r\n\r\nTo deploy solrcloud using this cookbook, below items are required:\r\n\r\n- a zookeeper server or cluster\r\n- configSet(s) to upload to zookeeper for collection/core\r\n- collection(s) name to deploy in solrcloud\r\n\r\n\r\n## SolrCloud configSet Cookbook / Environments / Versioning\r\n\r\n*Directory Structure*\r\n\r\nSorlCloud configSet stored in zookeeper are configured as file resources.\r\n\r\nEach configSet is stored under `node[:solrcloud][:zkconfigsets_cookbook]/files/default/configSet name`.\r\n\r\nconfigSet folder follows the standard of having a `conf` folder with all the configuration files.\r\n\r\nSo, the directory structure will look like - `node[:solrcloud][:zkconfigsets_cookbook]/files/default/configSet name/conf`.\r\n\r\n*Managing same configSet for Multiple Environments*\r\n\r\nManaging configSet configuration across environments can be achieved in different ways, like\r\n\r\n- maintain different `node[:solrcloud][:zkconfigsets_cookbook]` per environment\r\nOR\r\n- maintain a single cookbook with versioning\r\n\r\n\r\nSimply, update `node[:solrcloud][:zkconfigsets_cookbook]` attribute with your configSet cookbook and update metadata.rb\r\nfile with line:\r\n\r\n'depends `node[:solrcloud][:zkconfigsets_cookbook]`'.\r\n\r\n\r\n## Single Node SolrCloud Test Cluster Deployment\r\n\r\n\r\nAdjust the attributes according to your requirement. Below mentioned attributes\r\nwill work just fine for a single node solrcloud cluster.\r\n\r\n\r\n\t\"default_attributes\": {\r\n      \"solrcloud\": {\r\n\t\t\"zk_run\": true,\r\n        \"port\": \"8080\",\r\n        \"setup_user\": true,\r\n        \"manager\": true,\r\n        \"zkconfigsets\": {\r\n          \"samplecollection\": {}\r\n        },\r\n        \"collections\": {\r\n          \"samplecollection\": {\r\n            \"collection_config_name\": \"samplecollection\"\r\n          }\r\n        }\r\n      }\r\n  \t}\r\n\r\n\r\n## Multi Node Manager Attributes\r\n\r\nBelow attributes are crucial for Multi Node Cluster. It is not advised to enable below solrcloud attributes on all\r\nthe nodes in the cluster. Like, each new node will trigger a zookeeper configset re-upload. Creating new collection\r\nis better off maanged by one node to prevent a false collection state in the cluster.\r\n\r\n\r\n\t\"default_attributes\": {\r\n      \"solrcloud\": {\r\n      \t\"manage_collections\": true,\r\n      \t\"manage_zkconfigsets\": true,\r\n\r\n\r\n## Multi Node SolrCloud Test Cluster Deployment with zookeeper Cluster\r\n\r\n\r\nAdjust the attributes according to your requirement. Below mentioned attributes\r\nwill work just fine for a single node solrcloud cluster.\r\n\r\n\r\n\t\"default_attributes\": {\r\n      \"solrcloud\": {\r\n        \"solr_config\": {\r\n          \"solrcloud\": {\r\n            \"zk_host\": [\r\n              \"zookeeper_ip:zookeeper_port\"\r\n            ]\r\n          }\r\n\t\t},\r\n        \"port\": \"8080\",\r\n        \"setup_user\": true,\r\n      \t\"manage_collections\": true,\r\n      \t\"manage_zkconfigsets\": true,\r\n        \"zkconfigsets\": {\r\n          \"samplecollection\": {}\r\n        },\r\n        \"collections\": {\r\n          \"samplecollection\": {\r\n            \"collection_config_name\": \"samplecollection\"\r\n          }\r\n        }\r\n      }\r\n  \t}\r\n\r\n> Note: You might want to enable attribute `\"manager\": true` on limited cluster nodes. In a large\r\n> cluster, enabling this value on limited nodes would create less overhead for zookeeper.\r\n\r\n\r\n## Multi Node SolrCloud Test Cluster Deployment with embedded zookeeper\r\n\r\n\r\nAdjust the attributes according to your requirement. Below mentioned attributes\r\nwill work just fine for a single node solrcloud cluster.\r\n\r\n\r\nOn `any one` of the cluster node, enable attribute `node[:solrcloud][:zk_run]` and use its ip address as zookeeper server.\r\n\r\n\t\"default_attributes\": {\r\n      \"solrcloud\": {\r\n        \"solr_config\": {\r\n          \"solrcloud\": {\r\n            \"zk_host\": [\r\n              \"instance_with_zk_run_ip:zookeeper_port_default_2181\"\r\n            ]\r\n          }\r\n\t\t},\r\n        \"port\": \"8080\",\r\n        \"setup_user\": true,\r\n        \"zkconfigsets\": {\r\n          \"samplecollection\": {}\r\n        },\r\n        \"collections\": {\r\n          \"samplecollection\": {\r\n            \"collection_config_name\": \"samplecollection\"\r\n          }\r\n        }\r\n      }\r\n  \t}\r\n\r\n\r\n## Multiple SolrCloud Cluster Deployment\r\n\r\nTo deploy multiple clusters, simply create multiple roles with different zookeeper server or update\r\nnode attribute with respective cluster zookeeper server(s).\r\n\r\nZookeeper server attribute - `node[:solrcloud][:solr_config][:solrcloud][:zk_host]`\r\n\r\n\r\n## SolrCloud on HDFS Cluster Deployment\r\n\r\nSolrCloud on HDFS has not been tested yet, but configuration from Apache Solr documentation has been\r\nadded to the cookbook.\r\n\r\n\r\n## Tune Java Parameters for better Performance\r\n\r\nSome of the common java options tuning by [Shawn Heisey].\r\n\r\nNode attributes:\r\n\r\n    \"default_attributes\": {\r\n      \"solrcloud\": {\r\n        \"java_options\": [\r\n          \"-Xms1024m\",\r\n          \"-XX:+UseConcMarkSweepGC\",\r\n          \"-XX:CMSInitiatingOccupancyFraction=75\",\r\n          \"-XX:NewRatio=3\",\r\n          \"-XX:MaxTenuringThreshold=8\",\r\n          \"-XX:+CMSParallelRemarkEnabled\",\r\n          \"-XX:+ParallelRefProcEnabled\",\r\n          \"-XX:+AggressiveOpts\"\r\n        ]\r\n      }\r\n    }\r\n\r\n\r\n## Contributing\r\n\r\n1. Fork the repository on Github\r\n2. Create a named feature branch (like `add_component_x`)\r\n3. Write your change\r\n4. Write tests for your change (if applicable)\r\n5. Run the tests, ensuring they all pass\r\n6. Write description about changes\r\n7. Submit a Pull Request using Github\r\n\r\n\r\n## Copyright & License\r\n\r\nAuthors:: Virender Khatri and [Contributors]\r\n\r\nLicensed under the Apache License, Version 2.0 (the \"License\");\r\nyou may not use this file except in compliance with the License.\r\nYou may obtain a copy of the License at\r\n\r\n    http://www.apache.org/licenses/LICENSE-2.0\r\n\r\nUnless required by applicable law or agreed to in writing, software\r\ndistributed under the License is distributed on an \"AS IS\" BASIS,\r\nWITHOUT WARRANTIES OR CONDITIONS OF ANY KIND, either express or implied.\r\nSee the License for the specific language governing permissions and\r\nlimitations under the License.\r\n\r\n\r\n\r\n[Jetty]: http://wiki.apache.org/solr/SolrJetty\r\n[Apache Solr]: http://lucene.apache.org/solr/\r\n[solr on hdfs]: https://cwiki.apache.org/confluence/display/solr/Running+Solr+on+HDFS\r\n[Chef]: https://www.getchef.com/chef/\r\n[Contributors]: https://github.com/vkhatri/chef-solrcloud/graphs/contributors\r\n[Shawn Heisey]: https://wiki.apache.org/solr/ShawnHeisey\r\n","google":"","note":"Don't delete this file! It's used internally to help with page regeneration."}